devind_core/__init__.py
devind_core/apps.py
devind_core/filters.py
devind_core/management/commands/fs.py
devind_core/management/commands/update_seed.py
devind_core/managers/__init__.py
devind_core/managers/user_manager.py
devind_core/middleware/__init__.py
devind_core/middleware/lang_request_middleware.py
devind_core/middleware/readme.md
devind_core/middleware/session_middleware.py
devind_core/middleware/time_request_middleware.py
devind_core/middleware/token_auth_middleware.py
devind_core/migrations/0001_initial.py
devind_core/migrations/0002_auto_20220620_1644.py
devind_core/migrations/__init__.py
devind_core/models/__init__.py
devind_core/models/file.py
devind_core/models/log_request.py
devind_core/models/profile.py
devind_core/models/reset_password.py
devind_core/models/session.py
devind_core/models/settings.py
devind_core/models/user.py
devind_core/permissions/__init__.py
devind_core/permissions/file_permissions.py
devind_core/permissions/group_permission.py
devind_core/permissions/profile_permissions.py
devind_core/permissions/settings_permissions.py
devind_core/permissions/user_permissions.py
devind_core/schema/__init__.py
devind_core/schema/connections/countable_connection.py
devind_core/schema/mutations/__init__.py
devind_core/schema/mutations/file_mutations.py
devind_core/schema/mutations/group_mutations.py
devind_core/schema/mutations/profile_mutations.py
devind_core/schema/mutations/setting_mutations.py
devind_core/schema/mutations/support_mutations.py
devind_core/schema/mutations/user_mutations.py
devind_core/schema/queries/__init__.py
devind_core/schema/queries/group_queries.py
devind_core/schema/queries/profile_queries.py
devind_core/schema/queries/session_queries.py
devind_core/schema/queries/user_queries.py
devind_core/schema/subscriptions/__init__.py
devind_core/schema/subscriptions/base_subscription.py
devind_core/schema/types.py
devind_core/settings.py
devind_core/tasks/__init__.py
devind_core/tasks/file_tasks.py
devind_core/tests.py
devind_core-0.7.5.dist-info/LICENSE
devind_core-0.7.5.dist-info/WHEEL
devind_core-0.7.5.dist-info/METADATA
devind_core-0.7.5.dist-info/RECORD
