Metadata-Version: 2.1
Name: devind-core
Version: 0.7.5
Summary: Devind core.
Home-page: https://github.com/devind-team/devind-django-helpers
License: MIT
Keywords: django,graphene,core
Author: Victor
Author-email: lyferov@yandex.ru
Requires-Python: >=3.9,<4.0
Classifier: Framework :: Django
Classifier: License :: OSI Approved :: MIT License
Classifier: Operating System :: OS Independent
Classifier: Programming Language :: Python :: 3
Classifier: Programming Language :: Python :: 3.9
Classifier: Programming Language :: Python :: 3.10
Classifier: Programming Language :: Python :: 3.11
Classifier: Programming Language :: Python :: 3
Requires-Dist: Django (>=3,<4)
Requires-Dist: celery (>=5.2.7,<6.0.0)
Requires-Dist: channels (>=3.0.4,<4.0.0)
Requires-Dist: devind_helpers (>=0.7,<0.8)
Requires-Dist: django-auditlog (>=2.0.0,<3.0.0)
Requires-Dist: django-channels-graphql-ws (>=0.9.1,<0.10.0)
Requires-Dist: django-oauth-toolkit (>=1.7.1,<2.0.0)
Requires-Dist: graphene-django (>=2.15.0,<3.0.0)
Requires-Dist: graphene-file-upload (>=1.3.0,<2.0.0)
Requires-Dist: openpyxl (>=3.0.10,<4.0.0)
Requires-Dist: user-agents (>=2.2.0,<3.0.0)
Project-URL: Repository, https://github.com/devind-team/devind-django-helpers
